{
  "entries": {
    "tap": {
      "heroku/brew": {
        "revision": "3b6ca6a88b49e47a0fd7625eff10a2475ac7e1a4"
      },
      "homebrew/cask-fonts": {
        "revision": "0ed20f35d21ebc3f4f829689b101078718ad5ce1"
      },
      "mongodb/brew": {
        "revision": "a4246d1a3a245d7ebcc60f9a123b974770de59ab"
      },
      "homebrew/cask-versions": {
        "revision": "057d1202c4ac9d4059909260af8d13e20fbf8cab"
      }
    },
    "cask": {
      "1password": {
        "version": "8.10.33",
        "options": {
          "full_name": "1password"
        }
      },
      "adobe-acrobat-pro": {
        "version": "24.002.20759",
        "options": {
          "full_name": "adobe-acrobat-pro"
        }
      },
      "adobe-acrobat-reader": {
        "version": "24.002.20759",
        "options": {
          "full_name": "adobe-acrobat-reader"
        }
      },
      "android-studio": {
        "version": "2023.3.1.19",
        "options": {
          "full_name": "android-studio"
        }
      },
      "discord": {
        "version": "0.0.305",
        "options": {
          "full_name": "discord"
        }
      },
      "docker": {
        "version": "4.30.0,149282",
        "options": {
          "full_name": "docker"
        }
      },
      "expressvpn": {
        "version": "11.55.0.81819",
        "options": {
          "full_name": "expressvpn"
        }
      },
      "flutter": {
        "version": "3.22.1",
        "options": {
          "full_name": "flutter"
        }
      },
      "font-jetbrains-mono": {
        "version": "2.304",
        "options": {
          "full_name": "font-jetbrains-mono"
        }
      },
      "google-chrome": {
        "version": "125.0.6422.77",
        "options": {
          "full_name": "google-chrome"
        }
      },
      "google-drive": {
        "version": "126.0.6462.0,6462.0",
        "options": {
          "full_name": "google-drive"
        }
      },
      "iterm2": {
        "version": "3.5.0",
        "options": {
          "full_name": "iterm2"
        }
      },
      "ledger-live": {
        "version": "2.81.2",
        "options": {
          "full_name": "ledger-live"
        }
      },
      "mongodb-compass": {
        "version": "1.43.0",
        "options": {
          "full_name": "mongodb-compass"
        }
      },
      "ngrok": {
        "version": "3.10.0,22ssJXq6zv5,a",
        "options": {
          "full_name": "ngrok"
        }
      },
      "paintbrush": {
        "version": "2.6.0,20210402",
        "options": {
          "full_name": "paintbrush"
        }
      },
      "rectangle": {
        "version": "0.79",
        "options": {
          "full_name": "rectangle"
        }
      },
      "slack": {
        "version": "4.38.125",
        "options": {
          "full_name": "slack"
        }
      },
      "visual-studio-code": {
        "version": "1.89.1",
        "options": {
          "full_name": "visual-studio-code"
        }
      },
      "vlc": {
        "version": "3.0.20",
        "options": {
          "full_name": "vlc"
        }
      },
      "zoom": {
        "version": "6.0.10.34808",
        "options": {
          "full_name": "zoom"
        }
      },
      "zulu": {
        "version": "21.0.1,21.30.15-ca",
        "options": {
          "full_name": "zulu"
        }
      },
      "zulu11": {
        "version": "11.0.21,11.68.17-ca",
        "options": {
          "full_name": "zulu11"
        }
      },
      "zulu17": {
        "version": "17.0.11,17.50.19",
        "options": {
          "full_name": "zulu17"
        }
      },
      "reactotron": {
        "version": "3.7.0",
        "options": {
          "full_name": "reactotron"
        }
      },
      "1password-cli": {
        "version": "2.29.0",
        "options": {
          "full_name": "1password-cli"
        }
      },
      "zulu@17": {
        "version": null,
        "options": {
          "full_name": "zulu@17"
        }
      }
    },
    "brew": {
      "cocoapods": {
        "version": "1.15.2",
        "bottle": {
          "rebuild": 0,
          "root_url": "https://ghcr.io/v2/homebrew/core",
          "files": {
            "arm64_sonoma": {
              "cellar": ":any",
              "url": "https://ghcr.io/v2/homebrew/core/cocoapods/blobs/sha256:4f9825eaf19aba42fc19939c47c49b3d4e322d383f5a79ab029167351d5547c6",
              "sha256": "4f9825eaf19aba42fc19939c47c49b3d4e322d383f5a79ab029167351d5547c6"
            },
            "arm64_ventura": {
              "cellar": ":any",
              "url": "https://ghcr.io/v2/homebrew/core/cocoapods/blobs/sha256:e1729cced418772a8d8aa810c7cb153ec66db56a9b2cbec3e53adaaa576fb1ba",
              "sha256": "e1729cced418772a8d8aa810c7cb153ec66db56a9b2cbec3e53adaaa576fb1ba"
            },
            "arm64_monterey": {
              "cellar": ":any",
              "url": "https://ghcr.io/v2/homebrew/core/cocoapods/blobs/sha256:e8dc98276c80101c70aa14f6e736e1154b988f3b53f6be357b7a76cf776c3b4b",
              "sha256": "e8dc98276c80101c70aa14f6e736e1154b988f3b53f6be357b7a76cf776c3b4b"
            },
            "sonoma": {
              "cellar": ":any",
              "url": "https://ghcr.io/v2/homebrew/core/cocoapods/blobs/sha256:981c5baaab7a26258bfccfb7efc7141b9a88912b5fe06197ac07423fc436ed34",
              "sha256": "981c5baaab7a26258bfccfb7efc7141b9a88912b5fe06197ac07423fc436ed34"
            },
            "ventura": {
              "cellar": ":any",
              "url": "https://ghcr.io/v2/homebrew/core/cocoapods/blobs/sha256:1cf37b506f2b50d73a26b3b1e1f28009faeb66d6a3ec4671453ac6d360e96cba",
              "sha256": "1cf37b506f2b50d73a26b3b1e1f28009faeb66d6a3ec4671453ac6d360e96cba"
            },
            "monterey": {
              "cellar": ":any",
              "url": "https://ghcr.io/v2/homebrew/core/cocoapods/blobs/sha256:fa000679291ddbfa5792e8b04f71c106c4c3325116215ceb76e46f4c8ed7f85d",
              "sha256": "fa000679291ddbfa5792e8b04f71c106c4c3325116215ceb76e46f4c8ed7f85d"
            },
            "x86_64_linux": {
              "cellar": ":any_skip_relocation",
              "url": "https://ghcr.io/v2/homebrew/core/cocoapods/blobs/sha256:1cad9d3142ee7623d1ca22773dbeefa0e936e224aecef263a1657a91413c9958",
              "sha256": "1cad9d3142ee7623d1ca22773dbeefa0e936e224aecef263a1657a91413c9958"
            }
          }
        }
      },
      "coreutils": {
        "version": "9.5",
        "bottle": {
          "rebuild": 0,
          "root_url": "https://ghcr.io/v2/homebrew/core",
          "files": {
            "arm64_sonoma": {
              "cellar": "/opt/homebrew/Cellar",
              "url": "https://ghcr.io/v2/homebrew/core/coreutils/blobs/sha256:b2c643420d7d9de89385d86e0c3f5e9f9ae2404ce378db574dabbfce3ca37a91",
              "sha256": "b2c643420d7d9de89385d86e0c3f5e9f9ae2404ce378db574dabbfce3ca37a91"
            },
            "arm64_ventura": {
              "cellar": "/opt/homebrew/Cellar",
              "url": "https://ghcr.io/v2/homebrew/core/coreutils/blobs/sha256:0f889fb75ebc8e96aa1f38aff6ed1bc7e87c45b70f7644c7e1492f1f9480f352",
              "sha256": "0f889fb75ebc8e96aa1f38aff6ed1bc7e87c45b70f7644c7e1492f1f9480f352"
            },
            "arm64_monterey": {
              "cellar": "/opt/homebrew/Cellar",
              "url": "https://ghcr.io/v2/homebrew/core/coreutils/blobs/sha256:43bb62929309c51bb600e0d156b107ef147094445b29ada1387c222d9a2465c4",
              "sha256": "43bb62929309c51bb600e0d156b107ef147094445b29ada1387c222d9a2465c4"
            },
            "sonoma": {
              "cellar": "/usr/local/Cellar",
              "url": "https://ghcr.io/v2/homebrew/core/coreutils/blobs/sha256:19eccdcccfcacd67000acf89e3261174dfe30b0a764d10ccc39be82a4b37c0a5",
              "sha256": "19eccdcccfcacd67000acf89e3261174dfe30b0a764d10ccc39be82a4b37c0a5"
            },
            "ventura": {
              "cellar": "/usr/local/Cellar",
              "url": "https://ghcr.io/v2/homebrew/core/coreutils/blobs/sha256:7c8c3c6eab6032c379bb7266bf78e25b3b3d38d167c4eee92a7c023b131b86e0",
              "sha256": "7c8c3c6eab6032c379bb7266bf78e25b3b3d38d167c4eee92a7c023b131b86e0"
            },
            "monterey": {
              "cellar": "/usr/local/Cellar",
              "url": "https://ghcr.io/v2/homebrew/core/coreutils/blobs/sha256:44ce33f1d4d73b54bf312f48c9d93bd7a186f4ce1adc004c9f3168da004eee6c",
              "sha256": "44ce33f1d4d73b54bf312f48c9d93bd7a186f4ce1adc004c9f3168da004eee6c"
            },
            "x86_64_linux": {
              "cellar": "/home/linuxbrew/.linuxbrew/Cellar",
              "url": "https://ghcr.io/v2/homebrew/core/coreutils/blobs/sha256:e48884f502b3236e747b1280d5373d058b4bb47f872c99533d90ba2e730f3266",
              "sha256": "e48884f502b3236e747b1280d5373d058b4bb47f872c99533d90ba2e730f3266"
            }
          }
        }
      },
      "git": {
        "version": "2.45.1",
        "bottle": {
          "rebuild": 0,
          "root_url": "https://ghcr.io/v2/homebrew/core",
          "files": {
            "arm64_sonoma": {
              "cellar": "/opt/homebrew/Cellar",
              "url": "https://ghcr.io/v2/homebrew/core/git/blobs/sha256:afe93a73a2605a89e7c41ddb41159ee05081177a126507a9221265155139a5ef",
              "sha256": "afe93a73a2605a89e7c41ddb41159ee05081177a126507a9221265155139a5ef"
            },
            "arm64_ventura": {
              "cellar": "/opt/homebrew/Cellar",
              "url": "https://ghcr.io/v2/homebrew/core/git/blobs/sha256:f30916cb2799e8e9526f57331182737840bf6a49d6a286663a5e3f98527e97ee",
              "sha256": "f30916cb2799e8e9526f57331182737840bf6a49d6a286663a5e3f98527e97ee"
            },
            "arm64_monterey": {
              "cellar": "/opt/homebrew/Cellar",
              "url": "https://ghcr.io/v2/homebrew/core/git/blobs/sha256:133cafdf38f924f4ac75cfd55e044196f93ee98a07d13e9b9c1f601f906b15b7",
              "sha256": "133cafdf38f924f4ac75cfd55e044196f93ee98a07d13e9b9c1f601f906b15b7"
            },
            "sonoma": {
              "cellar": "/usr/local/Cellar",
              "url": "https://ghcr.io/v2/homebrew/core/git/blobs/sha256:9b7a1a74341999561dd0f8dc15525cbc95c5fa9ba6b7a4b1eee75ef35ff4184e",
              "sha256": "9b7a1a74341999561dd0f8dc15525cbc95c5fa9ba6b7a4b1eee75ef35ff4184e"
            },
            "ventura": {
              "cellar": "/usr/local/Cellar",
              "url": "https://ghcr.io/v2/homebrew/core/git/blobs/sha256:aae5afd95a2fc684b1ffa97f9397f11f50f6488b5ed39728771400342900bae0",
              "sha256": "aae5afd95a2fc684b1ffa97f9397f11f50f6488b5ed39728771400342900bae0"
            },
            "monterey": {
              "cellar": "/usr/local/Cellar",
              "url": "https://ghcr.io/v2/homebrew/core/git/blobs/sha256:59aefff18d6a17caf66ce097f3ef2c92e8c91612ab298349807c0688478cae9c",
              "sha256": "59aefff18d6a17caf66ce097f3ef2c92e8c91612ab298349807c0688478cae9c"
            },
            "x86_64_linux": {
              "cellar": "/home/linuxbrew/.linuxbrew/Cellar",
              "url": "https://ghcr.io/v2/homebrew/core/git/blobs/sha256:913bc3c739d4eeb50573dcdd35d9e3587e4313691838c09f05aca36b81f5bf35",
              "sha256": "913bc3c739d4eeb50573dcdd35d9e3587e4313691838c09f05aca36b81f5bf35"
            }
          }
        }
      },
      "heroku": {
        "version": "8.11.5",
        "bottle": false
      },
      "mas": {
        "version": "1.8.6",
        "bottle": {
          "rebuild": 0,
          "root_url": "https://ghcr.io/v2/homebrew/core",
          "files": {
            "arm64_sonoma": {
              "cellar": ":any_skip_relocation",
              "url": "https://ghcr.io/v2/homebrew/core/mas/blobs/sha256:7b11bfefcb43e9a423ff301f7bbc29b0fb86044bf93442f243c5a8a67d8d4869",
              "sha256": "7b11bfefcb43e9a423ff301f7bbc29b0fb86044bf93442f243c5a8a67d8d4869"
            },
            "arm64_ventura": {
              "cellar": ":any_skip_relocation",
              "url": "https://ghcr.io/v2/homebrew/core/mas/blobs/sha256:e49511dd1283813c4420aec9fc3b3167d18f9fdbb51d82b1e479b628d5312342",
              "sha256": "e49511dd1283813c4420aec9fc3b3167d18f9fdbb51d82b1e479b628d5312342"
            },
            "arm64_monterey": {
              "cellar": ":any_skip_relocation",
              "url": "https://ghcr.io/v2/homebrew/core/mas/blobs/sha256:379d46e2657be295321f1603dc1df28130ea0b5b264ceb192a9ba488d77c7a98",
              "sha256": "379d46e2657be295321f1603dc1df28130ea0b5b264ceb192a9ba488d77c7a98"
            },
            "arm64_big_sur": {
              "cellar": ":any_skip_relocation",
              "url": "https://ghcr.io/v2/homebrew/core/mas/blobs/sha256:918a1484de106940f7bebc936e1ded87d7b65652054b09204887ad0651937ec4",
              "sha256": "918a1484de106940f7bebc936e1ded87d7b65652054b09204887ad0651937ec4"
            },
            "sonoma": {
              "cellar": ":any_skip_relocation",
              "url": "https://ghcr.io/v2/homebrew/core/mas/blobs/sha256:24e3057991ea1eed52eb4a27c0f17d794106770621e5a8bb975477dae135b82d",
              "sha256": "24e3057991ea1eed52eb4a27c0f17d794106770621e5a8bb975477dae135b82d"
            },
            "ventura": {
              "cellar": ":any_skip_relocation",
              "url": "https://ghcr.io/v2/homebrew/core/mas/blobs/sha256:6ef7788e28c46cdc0f916812f49dfeb1fabf2240a8c36f33ce34bcfb9df1502f",
              "sha256": "6ef7788e28c46cdc0f916812f49dfeb1fabf2240a8c36f33ce34bcfb9df1502f"
            },
            "monterey": {
              "cellar": ":any_skip_relocation",
              "url": "https://ghcr.io/v2/homebrew/core/mas/blobs/sha256:6b313f2f66d028cb7782c108d6e502ce73ccb9c08fac3bece0b057fcce5c4689",
              "sha256": "6b313f2f66d028cb7782c108d6e502ce73ccb9c08fac3bece0b057fcce5c4689"
            },
            "big_sur": {
              "cellar": ":any_skip_relocation",
              "url": "https://ghcr.io/v2/homebrew/core/mas/blobs/sha256:50b50f51219143fcb69c730b52b74011a76104f66348ea727d0200f7b375ae25",
              "sha256": "50b50f51219143fcb69c730b52b74011a76104f66348ea727d0200f7b375ae25"
            },
            "catalina": {
              "cellar": ":any_skip_relocation",
              "url": "https://ghcr.io/v2/homebrew/core/mas/blobs/sha256:d241d3b9156b033f3d2c31684a44de726297e07fd9bd5e3ccc4c36e4f1c3baf3",
              "sha256": "d241d3b9156b033f3d2c31684a44de726297e07fd9bd5e3ccc4c36e4f1c3baf3"
            }
          }
        }
      },
      "mongodb-community": {
        "version": "7.0.11",
        "bottle": false
      },
      "node": {
        "version": "21.1.0",
        "bottle": {
          "rebuild": 0,
          "root_url": "https://ghcr.io/v2/homebrew/core",
          "files": {
            "arm64_sonoma": {
              "cellar": "/opt/homebrew/Cellar",
              "url": "https://ghcr.io/v2/homebrew/core/node/blobs/sha256:2c62cf35b3e83dcd91a31d6f93cf6eacdbeb20225d4240fafb59d9eee2439805",
              "sha256": "2c62cf35b3e83dcd91a31d6f93cf6eacdbeb20225d4240fafb59d9eee2439805"
            },
            "arm64_ventura": {
              "cellar": "/opt/homebrew/Cellar",
              "url": "https://ghcr.io/v2/homebrew/core/node/blobs/sha256:b04b18885aeecd0c29c81de9e80e7c155a89e22e48cfd0dd7e285c3fcf5732cb",
              "sha256": "b04b18885aeecd0c29c81de9e80e7c155a89e22e48cfd0dd7e285c3fcf5732cb"
            },
            "arm64_monterey": {
              "cellar": "/opt/homebrew/Cellar",
              "url": "https://ghcr.io/v2/homebrew/core/node/blobs/sha256:965f5871990c23356d05f2d7ceeb2b07ea465b6ab02ccae8e83f552618ef8920",
              "sha256": "965f5871990c23356d05f2d7ceeb2b07ea465b6ab02ccae8e83f552618ef8920"
            },
            "sonoma": {
              "cellar": "/usr/local/Cellar",
              "url": "https://ghcr.io/v2/homebrew/core/node/blobs/sha256:4804bb076d76ccab4d573115e0b25f65f75305d468427b594928541d2bd4ceff",
              "sha256": "4804bb076d76ccab4d573115e0b25f65f75305d468427b594928541d2bd4ceff"
            },
            "ventura": {
              "cellar": "/usr/local/Cellar",
              "url": "https://ghcr.io/v2/homebrew/core/node/blobs/sha256:70824a6d356938214e73dfb01c781609e409b2ac2e1d377e7d5c5c1399fd2488",
              "sha256": "70824a6d356938214e73dfb01c781609e409b2ac2e1d377e7d5c5c1399fd2488"
            },
            "monterey": {
              "cellar": "/usr/local/Cellar",
              "url": "https://ghcr.io/v2/homebrew/core/node/blobs/sha256:5bd2b193dcfd48d784ab9a6fc309e78cd9dc8c36bb2dc97120721d333d3d9bee",
              "sha256": "5bd2b193dcfd48d784ab9a6fc309e78cd9dc8c36bb2dc97120721d333d3d9bee"
            },
            "x86_64_linux": {
              "cellar": "/home/linuxbrew/.linuxbrew/Cellar",
              "url": "https://ghcr.io/v2/homebrew/core/node/blobs/sha256:3bb614fb3dd8a8ab2c6ac64c8d3f815c6afdee329884dd6c4b079b9b174b2e9a",
              "sha256": "3bb614fb3dd8a8ab2c6ac64c8d3f815c6afdee329884dd6c4b079b9b174b2e9a"
            }
          }
        }
      },
      "redis": {
        "version": "7.2.5",
        "bottle": {
          "rebuild": 0,
          "root_url": "https://ghcr.io/v2/homebrew/core",
          "files": {
            "arm64_sonoma": {
              "cellar": ":any",
              "url": "https://ghcr.io/v2/homebrew/core/redis/blobs/sha256:bc4c2bb74037b80b2566938f7249c1052f8e493af8ee7b57e5ee14e19c19411e",
              "sha256": "bc4c2bb74037b80b2566938f7249c1052f8e493af8ee7b57e5ee14e19c19411e"
            },
            "arm64_ventura": {
              "cellar": ":any",
              "url": "https://ghcr.io/v2/homebrew/core/redis/blobs/sha256:c40b3cf2351377a3e71d5a8562b4a62e94b65cb736d3438b67465cf2aacecf2e",
              "sha256": "c40b3cf2351377a3e71d5a8562b4a62e94b65cb736d3438b67465cf2aacecf2e"
            },
            "arm64_monterey": {
              "cellar": ":any",
              "url": "https://ghcr.io/v2/homebrew/core/redis/blobs/sha256:c749644cda76a63f76cbc39fd8f2021ab959a4e1eb8c8ff5dfe5638803c80333",
              "sha256": "c749644cda76a63f76cbc39fd8f2021ab959a4e1eb8c8ff5dfe5638803c80333"
            },
            "sonoma": {
              "cellar": ":any",
              "url": "https://ghcr.io/v2/homebrew/core/redis/blobs/sha256:1415fc1040dff3bd1955d3440d9627d80a23d623801cc4b16cb07b9d4a921c0b",
              "sha256": "1415fc1040dff3bd1955d3440d9627d80a23d623801cc4b16cb07b9d4a921c0b"
            },
            "ventura": {
              "cellar": ":any",
              "url": "https://ghcr.io/v2/homebrew/core/redis/blobs/sha256:9c5f7c63a52f880ecf43d44d533a3b4c05089030442e1652cdfe3cc7ea88ed93",
              "sha256": "9c5f7c63a52f880ecf43d44d533a3b4c05089030442e1652cdfe3cc7ea88ed93"
            },
            "monterey": {
              "cellar": ":any",
              "url": "https://ghcr.io/v2/homebrew/core/redis/blobs/sha256:4c97e9718bd50ee80e139936e0b5fb6fd73879051ed7e9d6bddc5eae0d671347",
              "sha256": "4c97e9718bd50ee80e139936e0b5fb6fd73879051ed7e9d6bddc5eae0d671347"
            },
            "x86_64_linux": {
              "cellar": ":any_skip_relocation",
              "url": "https://ghcr.io/v2/homebrew/core/redis/blobs/sha256:d782e9fcee0d8a104ba5071709fb183ce77edb40f153c971001baaa025029910",
              "sha256": "d782e9fcee0d8a104ba5071709fb183ce77edb40f153c971001baaa025029910"
            }
          }
        }
      },
      "watchman": {
        "version": "2024.05.06.00",
        "bottle": {
          "rebuild": 0,
          "root_url": "https://ghcr.io/v2/homebrew/core",
          "files": {
            "arm64_sonoma": {
              "cellar": ":any",
              "url": "https://ghcr.io/v2/homebrew/core/watchman/blobs/sha256:9410b4b119812956ec5c064d97bd431d40819228fb796762ef4939cc1ef5fd06",
              "sha256": "9410b4b119812956ec5c064d97bd431d40819228fb796762ef4939cc1ef5fd06"
            },
            "arm64_ventura": {
              "cellar": ":any",
              "url": "https://ghcr.io/v2/homebrew/core/watchman/blobs/sha256:faa946e214d25678421fd6c4408f7d6887442bd3caf8c2e4341b1be965725bdf",
              "sha256": "faa946e214d25678421fd6c4408f7d6887442bd3caf8c2e4341b1be965725bdf"
            },
            "arm64_monterey": {
              "cellar": ":any",
              "url": "https://ghcr.io/v2/homebrew/core/watchman/blobs/sha256:eaa4dc834ad4a577b00a6577c6a78c51987c7ffae5f8cee1052c05df7c70bff3",
              "sha256": "eaa4dc834ad4a577b00a6577c6a78c51987c7ffae5f8cee1052c05df7c70bff3"
            },
            "sonoma": {
              "cellar": ":any",
              "url": "https://ghcr.io/v2/homebrew/core/watchman/blobs/sha256:d8488eb7b1189a56aecd3a20ad30317f135d7f72e1562e181802f0f5ce341263",
              "sha256": "d8488eb7b1189a56aecd3a20ad30317f135d7f72e1562e181802f0f5ce341263"
            },
            "ventura": {
              "cellar": ":any",
              "url": "https://ghcr.io/v2/homebrew/core/watchman/blobs/sha256:509d971921f135c36e21a6a64d0542f655ff495eb838dd99d4ef3fd59e161751",
              "sha256": "509d971921f135c36e21a6a64d0542f655ff495eb838dd99d4ef3fd59e161751"
            },
            "monterey": {
              "cellar": ":any",
              "url": "https://ghcr.io/v2/homebrew/core/watchman/blobs/sha256:95423e2cb2927a8b30d204258f53d15f1414ca0f0c24836e147863e3f529e67e",
              "sha256": "95423e2cb2927a8b30d204258f53d15f1414ca0f0c24836e147863e3f529e67e"
            },
            "x86_64_linux": {
              "cellar": ":any_skip_relocation",
              "url": "https://ghcr.io/v2/homebrew/core/watchman/blobs/sha256:24919bbc7c971be7fe37ea161ea4268604c67dcfe6435dc2258b2050cb4495c3",
              "sha256": "24919bbc7c971be7fe37ea161ea4268604c67dcfe6435dc2258b2050cb4495c3"
            }
          }
        }
      },
      "ios-deploy": {
        "version": "1.12.2",
        "bottle": {
          "rebuild": 0,
          "root_url": "https://ghcr.io/v2/homebrew/core",
          "files": {
            "arm64_sonoma": {
              "cellar": ":any_skip_relocation",
              "url": "https://ghcr.io/v2/homebrew/core/ios-deploy/blobs/sha256:6d9ac2ff01049d41618a63ef47738fe9e01cf9b77154b9773bde884a42dd31e1",
              "sha256": "6d9ac2ff01049d41618a63ef47738fe9e01cf9b77154b9773bde884a42dd31e1"
            },
            "arm64_ventura": {
              "cellar": ":any_skip_relocation",
              "url": "https://ghcr.io/v2/homebrew/core/ios-deploy/blobs/sha256:5c87b96b6692afa7b56724cb2e1a0f1cf1e8065f803266c8d83a7d5623496896",
              "sha256": "5c87b96b6692afa7b56724cb2e1a0f1cf1e8065f803266c8d83a7d5623496896"
            },
            "arm64_monterey": {
              "cellar": ":any_skip_relocation",
              "url": "https://ghcr.io/v2/homebrew/core/ios-deploy/blobs/sha256:eae3172eaea91a064b40f05f508d4d4a3d9c18cdba920fec27be57477cfd5ec4",
              "sha256": "eae3172eaea91a064b40f05f508d4d4a3d9c18cdba920fec27be57477cfd5ec4"
            },
            "arm64_big_sur": {
              "cellar": ":any_skip_relocation",
              "url": "https://ghcr.io/v2/homebrew/core/ios-deploy/blobs/sha256:8eddbc577a5cfa12da1fa5e0c6a40ae19f2b20c275326f3e9db6ce95bef0c640",
              "sha256": "8eddbc577a5cfa12da1fa5e0c6a40ae19f2b20c275326f3e9db6ce95bef0c640"
            },
            "sonoma": {
              "cellar": ":any_skip_relocation",
              "url": "https://ghcr.io/v2/homebrew/core/ios-deploy/blobs/sha256:91d82a87a7a1ed736955a407d2fba49053222fd3ab4a4af23123cb6fd6b7ad4b",
              "sha256": "91d82a87a7a1ed736955a407d2fba49053222fd3ab4a4af23123cb6fd6b7ad4b"
            },
            "ventura": {
              "cellar": ":any_skip_relocation",
              "url": "https://ghcr.io/v2/homebrew/core/ios-deploy/blobs/sha256:9c9ca5f1ced69ffa9d96409dce25c135560edce0082391f24c84493b8822fd04",
              "sha256": "9c9ca5f1ced69ffa9d96409dce25c135560edce0082391f24c84493b8822fd04"
            },
            "monterey": {
              "cellar": ":any_skip_relocation",
              "url": "https://ghcr.io/v2/homebrew/core/ios-deploy/blobs/sha256:245e3e9a9334e2fc2ee3e1123493849bbfdec93dd33fad32c45dff32da512e96",
              "sha256": "245e3e9a9334e2fc2ee3e1123493849bbfdec93dd33fad32c45dff32da512e96"
            },
            "big_sur": {
              "cellar": ":any_skip_relocation",
              "url": "https://ghcr.io/v2/homebrew/core/ios-deploy/blobs/sha256:b04cc3456def885207da127501db9e3e8defb9b108f1aae2f358e8498d6e8f16",
              "sha256": "b04cc3456def885207da127501db9e3e8defb9b108f1aae2f358e8498d6e8f16"
            }
          }
        }
      },
      "tree": {
        "version": "2.1.1_1",
        "bottle": {
          "rebuild": 0,
          "root_url": "https://ghcr.io/v2/homebrew/core",
          "files": {
            "arm64_sonoma": {
              "cellar": ":any_skip_relocation",
              "url": "https://ghcr.io/v2/homebrew/core/tree/blobs/sha256:2d1c490c83719c983ec360085e9d0049418ff424259bc00122869f8acf68ed63",
              "sha256": "2d1c490c83719c983ec360085e9d0049418ff424259bc00122869f8acf68ed63"
            },
            "arm64_ventura": {
              "cellar": ":any_skip_relocation",
              "url": "https://ghcr.io/v2/homebrew/core/tree/blobs/sha256:13b597dcee0eec0e8d3a7f864dfb5713d812605092bf1e417c765e788d0c0d31",
              "sha256": "13b597dcee0eec0e8d3a7f864dfb5713d812605092bf1e417c765e788d0c0d31"
            },
            "arm64_monterey": {
              "cellar": ":any_skip_relocation",
              "url": "https://ghcr.io/v2/homebrew/core/tree/blobs/sha256:0bd195b460f491c6e71b0277efb3c4cdbab8b6d814072519ade39e5ca257b048",
              "sha256": "0bd195b460f491c6e71b0277efb3c4cdbab8b6d814072519ade39e5ca257b048"
            },
            "sonoma": {
              "cellar": ":any_skip_relocation",
              "url": "https://ghcr.io/v2/homebrew/core/tree/blobs/sha256:af3d14eb91e4bf756bb5ef5f6a489aeb33e6cf5fc4f72c99d70352bec364e282",
              "sha256": "af3d14eb91e4bf756bb5ef5f6a489aeb33e6cf5fc4f72c99d70352bec364e282"
            },
            "ventura": {
              "cellar": ":any_skip_relocation",
              "url": "https://ghcr.io/v2/homebrew/core/tree/blobs/sha256:da304661d82c58ee3d4a14f80479d15d3405ca4c1be78b6085f7c62e67f79412",
              "sha256": "da304661d82c58ee3d4a14f80479d15d3405ca4c1be78b6085f7c62e67f79412"
            },
            "monterey": {
              "cellar": ":any_skip_relocation",
              "url": "https://ghcr.io/v2/homebrew/core/tree/blobs/sha256:13a0875d7da74de5ccfd1c6d3bd6167d2c4c0d7d4d747cc3ebb377fad60df365",
              "sha256": "13a0875d7da74de5ccfd1c6d3bd6167d2c4c0d7d4d747cc3ebb377fad60df365"
            },
            "x86_64_linux": {
              "cellar": ":any_skip_relocation",
              "url": "https://ghcr.io/v2/homebrew/core/tree/blobs/sha256:48bf95e7ef6c5f14db8a551b3ba22db93613f39ad04985f2edd3d34754daf89e",
              "sha256": "48bf95e7ef6c5f14db8a551b3ba22db93613f39ad04985f2edd3d34754daf89e"
            }
          }
        }
      },
      "fastlane": {
        "version": "2.220.0",
        "bottle": {
          "rebuild": 0,
          "root_url": "https://ghcr.io/v2/homebrew/core",
          "files": {
            "arm64_sonoma": {
              "cellar": ":any",
              "url": "https://ghcr.io/v2/homebrew/core/fastlane/blobs/sha256:e3be53e4fd58f2708b592714adcb0c984069f183dea610abe420cf1060ad49f7",
              "sha256": "e3be53e4fd58f2708b592714adcb0c984069f183dea610abe420cf1060ad49f7"
            },
            "arm64_ventura": {
              "cellar": ":any",
              "url": "https://ghcr.io/v2/homebrew/core/fastlane/blobs/sha256:0c162caf307f541439ecac614cc70e09f9741c4ae8af3a70273b4634fa41ae19",
              "sha256": "0c162caf307f541439ecac614cc70e09f9741c4ae8af3a70273b4634fa41ae19"
            },
            "arm64_monterey": {
              "cellar": ":any",
              "url": "https://ghcr.io/v2/homebrew/core/fastlane/blobs/sha256:7022c9f08c8bdf092098432afe2075c796a82e7a23183dd84215142d9e32e2b7",
              "sha256": "7022c9f08c8bdf092098432afe2075c796a82e7a23183dd84215142d9e32e2b7"
            },
            "sonoma": {
              "cellar": ":any",
              "url": "https://ghcr.io/v2/homebrew/core/fastlane/blobs/sha256:6a3ae8a29fde517c88eb20d56d386733c7bcd6ebb09e584b06403fd070e4c4e6",
              "sha256": "6a3ae8a29fde517c88eb20d56d386733c7bcd6ebb09e584b06403fd070e4c4e6"
            },
            "ventura": {
              "cellar": ":any",
              "url": "https://ghcr.io/v2/homebrew/core/fastlane/blobs/sha256:fbafd5ec6f5bdfb082994af5b3725c57e39e6720312eaf5a042f0a80be1d6999",
              "sha256": "fbafd5ec6f5bdfb082994af5b3725c57e39e6720312eaf5a042f0a80be1d6999"
            },
            "monterey": {
              "cellar": ":any",
              "url": "https://ghcr.io/v2/homebrew/core/fastlane/blobs/sha256:9c64f195d2df3e31f66d6cd99e8b75e40679ec4a0ccbfc363ca6265b4be783b5",
              "sha256": "9c64f195d2df3e31f66d6cd99e8b75e40679ec4a0ccbfc363ca6265b4be783b5"
            },
            "x86_64_linux": {
              "cellar": ":any_skip_relocation",
              "url": "https://ghcr.io/v2/homebrew/core/fastlane/blobs/sha256:084260d00ab6786aff812a2833206e9ee20a55d2960a7a45c0f9fe3ff7a072af",
              "sha256": "084260d00ab6786aff812a2833206e9ee20a55d2960a7a45c0f9fe3ff7a072af"
            }
          }
        }
      },
      "awscli": {
        "version": "2.15.56",
        "bottle": {
          "rebuild": 0,
          "root_url": "https://ghcr.io/v2/homebrew/core",
          "files": {
            "arm64_sonoma": {
              "cellar": ":any",
              "url": "https://ghcr.io/v2/homebrew/core/awscli/blobs/sha256:c13b0b34282ded9d484a55963cf17eaa36a65e7764fca9c1131ba952dd2a6337",
              "sha256": "c13b0b34282ded9d484a55963cf17eaa36a65e7764fca9c1131ba952dd2a6337"
            },
            "arm64_ventura": {
              "cellar": ":any",
              "url": "https://ghcr.io/v2/homebrew/core/awscli/blobs/sha256:1f856fc95662a50c2629a0ca9678d5285dfd8a8260899d295416615ba584d665",
              "sha256": "1f856fc95662a50c2629a0ca9678d5285dfd8a8260899d295416615ba584d665"
            },
            "arm64_monterey": {
              "cellar": ":any",
              "url": "https://ghcr.io/v2/homebrew/core/awscli/blobs/sha256:a52121cdaa5dc5f9bab9b1c975adbe3388151e73cf071db0107dc0f1243f334c",
              "sha256": "a52121cdaa5dc5f9bab9b1c975adbe3388151e73cf071db0107dc0f1243f334c"
            },
            "sonoma": {
              "cellar": ":any",
              "url": "https://ghcr.io/v2/homebrew/core/awscli/blobs/sha256:28a9d0a9a482ef42f36abfd10ee5b2a087c8576f4adaf1e399057bdb5c466fa8",
              "sha256": "28a9d0a9a482ef42f36abfd10ee5b2a087c8576f4adaf1e399057bdb5c466fa8"
            },
            "ventura": {
              "cellar": ":any",
              "url": "https://ghcr.io/v2/homebrew/core/awscli/blobs/sha256:76990458dd6280349cc547f8e1ee53e0839a1c79bc599087fb90ad9770a1d1da",
              "sha256": "76990458dd6280349cc547f8e1ee53e0839a1c79bc599087fb90ad9770a1d1da"
            },
            "monterey": {
              "cellar": ":any",
              "url": "https://ghcr.io/v2/homebrew/core/awscli/blobs/sha256:32e3a95890ee3bff3f11a96f6b2845b2229036cee720a286dc9a7eaac43fe64e",
              "sha256": "32e3a95890ee3bff3f11a96f6b2845b2229036cee720a286dc9a7eaac43fe64e"
            },
            "x86_64_linux": {
              "cellar": ":any_skip_relocation",
              "url": "https://ghcr.io/v2/homebrew/core/awscli/blobs/sha256:9bd20bed66becb8127bc546539f62ed32a323f03547092fa2cb93d5882583cb7",
              "sha256": "9bd20bed66becb8127bc546539f62ed32a323f03547092fa2cb93d5882583cb7"
            }
          }
        }
      },
      "opentofu": {
        "version": "1.7.1",
        "bottle": {
          "rebuild": 0,
          "root_url": "https://ghcr.io/v2/homebrew/core",
          "files": {
            "arm64_sonoma": {
              "cellar": ":any_skip_relocation",
              "url": "https://ghcr.io/v2/homebrew/core/opentofu/blobs/sha256:5a52ad0d92cafa7ea6c4aff04757091eb0a36b9c667a35231873ab5aa405ee46",
              "sha256": "5a52ad0d92cafa7ea6c4aff04757091eb0a36b9c667a35231873ab5aa405ee46"
            },
            "arm64_ventura": {
              "cellar": ":any_skip_relocation",
              "url": "https://ghcr.io/v2/homebrew/core/opentofu/blobs/sha256:e8897c04f76a8ddaf59f417ceb4a7f431e5a35cbf1b9d81a0fa83bcd46bfdb4d",
              "sha256": "e8897c04f76a8ddaf59f417ceb4a7f431e5a35cbf1b9d81a0fa83bcd46bfdb4d"
            },
            "arm64_monterey": {
              "cellar": ":any_skip_relocation",
              "url": "https://ghcr.io/v2/homebrew/core/opentofu/blobs/sha256:48d459ac9a8e115c760135dc32900bd05f89512b9b5820d57cc87751e29bf00b",
              "sha256": "48d459ac9a8e115c760135dc32900bd05f89512b9b5820d57cc87751e29bf00b"
            },
            "sonoma": {
              "cellar": ":any_skip_relocation",
              "url": "https://ghcr.io/v2/homebrew/core/opentofu/blobs/sha256:7ad23e9262b5ae6f04c95588d989b4127e08e3daeeed31d6c6441cd11206f2e4",
              "sha256": "7ad23e9262b5ae6f04c95588d989b4127e08e3daeeed31d6c6441cd11206f2e4"
            },
            "ventura": {
              "cellar": ":any_skip_relocation",
              "url": "https://ghcr.io/v2/homebrew/core/opentofu/blobs/sha256:5dc9869cccf6cc0ace216ef42fd9e8dbc2053281a002a0a0b266a24590d53a7c",
              "sha256": "5dc9869cccf6cc0ace216ef42fd9e8dbc2053281a002a0a0b266a24590d53a7c"
            },
            "monterey": {
              "cellar": ":any_skip_relocation",
              "url": "https://ghcr.io/v2/homebrew/core/opentofu/blobs/sha256:98f568c903d303e7e0f4f364c3c7bdcacff97c7b5f0c240e88ca0c9c26d33650",
              "sha256": "98f568c903d303e7e0f4f364c3c7bdcacff97c7b5f0c240e88ca0c9c26d33650"
            },
            "x86_64_linux": {
              "cellar": ":any_skip_relocation",
              "url": "https://ghcr.io/v2/homebrew/core/opentofu/blobs/sha256:472dda53730a96cf8ab846a50a5f931d634ea1b491204bdd41db4ae27bdb81fa",
              "sha256": "472dda53730a96cf8ab846a50a5f931d634ea1b491204bdd41db4ae27bdb81fa"
            }
          }
        }
      },
      "python": {
        "version": "3.12.3",
        "bottle": {
          "rebuild": 0,
          "root_url": "https://ghcr.io/v2/homebrew/core",
          "files": {
            "arm64_sonoma": {
              "cellar": "/opt/homebrew/Cellar",
              "url": "https://ghcr.io/v2/homebrew/core/python/3.12/blobs/sha256:fd301f96783de7d57e8d704ca0967e5cf111350acbf1ad8bec36fa27bb75fc3c",
              "sha256": "fd301f96783de7d57e8d704ca0967e5cf111350acbf1ad8bec36fa27bb75fc3c"
            },
            "arm64_ventura": {
              "cellar": "/opt/homebrew/Cellar",
              "url": "https://ghcr.io/v2/homebrew/core/python/3.12/blobs/sha256:94baa02aa52145f2a41a11ef2f12787510ab31c449457e334abd9f09b126c01f",
              "sha256": "94baa02aa52145f2a41a11ef2f12787510ab31c449457e334abd9f09b126c01f"
            },
            "arm64_monterey": {
              "cellar": "/opt/homebrew/Cellar",
              "url": "https://ghcr.io/v2/homebrew/core/python/3.12/blobs/sha256:a04e80f97f70f22b4ca6dc15160585bf4f7863c689497e38a44b984e9c5f533e",
              "sha256": "a04e80f97f70f22b4ca6dc15160585bf4f7863c689497e38a44b984e9c5f533e"
            },
            "sonoma": {
              "cellar": "/usr/local/Cellar",
              "url": "https://ghcr.io/v2/homebrew/core/python/3.12/blobs/sha256:2bd309f8e329a645ac48a64e7b7983accf6773711491f635c9c5ed5c5f3a78fb",
              "sha256": "2bd309f8e329a645ac48a64e7b7983accf6773711491f635c9c5ed5c5f3a78fb"
            },
            "ventura": {
              "cellar": "/usr/local/Cellar",
              "url": "https://ghcr.io/v2/homebrew/core/python/3.12/blobs/sha256:9f5d156dee8517f0dd0bd7542974787cd38156bab4f897c4700d5787106e02a5",
              "sha256": "9f5d156dee8517f0dd0bd7542974787cd38156bab4f897c4700d5787106e02a5"
            },
            "monterey": {
              "cellar": "/usr/local/Cellar",
              "url": "https://ghcr.io/v2/homebrew/core/python/3.12/blobs/sha256:75ae75d6dafd805e42ba57d823d4dd8ffdbfde545ccc0340a2229ec183619274",
              "sha256": "75ae75d6dafd805e42ba57d823d4dd8ffdbfde545ccc0340a2229ec183619274"
            },
            "x86_64_linux": {
              "cellar": "/home/linuxbrew/.linuxbrew/Cellar",
              "url": "https://ghcr.io/v2/homebrew/core/python/3.12/blobs/sha256:faa009be56acac74433c08417d4ba15d65faae30535edc465601e33324c399d3",
              "sha256": "faa009be56acac74433c08417d4ba15d65faae30535edc465601e33324c399d3"
            }
          }
        }
      },
      "python@3.12": {
        "version": "3.12.3",
        "bottle": {
          "rebuild": 0,
          "root_url": "https://ghcr.io/v2/homebrew/core",
          "files": {
            "arm64_sonoma": {
              "cellar": "/opt/homebrew/Cellar",
              "url": "https://ghcr.io/v2/homebrew/core/python/3.12/blobs/sha256:fd301f96783de7d57e8d704ca0967e5cf111350acbf1ad8bec36fa27bb75fc3c",
              "sha256": "fd301f96783de7d57e8d704ca0967e5cf111350acbf1ad8bec36fa27bb75fc3c"
            },
            "arm64_ventura": {
              "cellar": "/opt/homebrew/Cellar",
              "url": "https://ghcr.io/v2/homebrew/core/python/3.12/blobs/sha256:94baa02aa52145f2a41a11ef2f12787510ab31c449457e334abd9f09b126c01f",
              "sha256": "94baa02aa52145f2a41a11ef2f12787510ab31c449457e334abd9f09b126c01f"
            },
            "arm64_monterey": {
              "cellar": "/opt/homebrew/Cellar",
              "url": "https://ghcr.io/v2/homebrew/core/python/3.12/blobs/sha256:a04e80f97f70f22b4ca6dc15160585bf4f7863c689497e38a44b984e9c5f533e",
              "sha256": "a04e80f97f70f22b4ca6dc15160585bf4f7863c689497e38a44b984e9c5f533e"
            },
            "sonoma": {
              "cellar": "/usr/local/Cellar",
              "url": "https://ghcr.io/v2/homebrew/core/python/3.12/blobs/sha256:2bd309f8e329a645ac48a64e7b7983accf6773711491f635c9c5ed5c5f3a78fb",
              "sha256": "2bd309f8e329a645ac48a64e7b7983accf6773711491f635c9c5ed5c5f3a78fb"
            },
            "ventura": {
              "cellar": "/usr/local/Cellar",
              "url": "https://ghcr.io/v2/homebrew/core/python/3.12/blobs/sha256:9f5d156dee8517f0dd0bd7542974787cd38156bab4f897c4700d5787106e02a5",
              "sha256": "9f5d156dee8517f0dd0bd7542974787cd38156bab4f897c4700d5787106e02a5"
            },
            "monterey": {
              "cellar": "/usr/local/Cellar",
              "url": "https://ghcr.io/v2/homebrew/core/python/3.12/blobs/sha256:75ae75d6dafd805e42ba57d823d4dd8ffdbfde545ccc0340a2229ec183619274",
              "sha256": "75ae75d6dafd805e42ba57d823d4dd8ffdbfde545ccc0340a2229ec183619274"
            },
            "x86_64_linux": {
              "cellar": "/home/linuxbrew/.linuxbrew/Cellar",
              "url": "https://ghcr.io/v2/homebrew/core/python/3.12/blobs/sha256:faa009be56acac74433c08417d4ba15d65faae30535edc465601e33324c399d3",
              "sha256": "faa009be56acac74433c08417d4ba15d65faae30535edc465601e33324c399d3"
            }
          }
        }
      }
    },
    "mas": {
      "GarageBand": {
        "id": "682658836",
        "version": "10.4.11"
      },
      "iMovie": {
        "id": "408981434",
        "version": "10.4"
      },
      "Xcode": {
        "id": "497799835",
        "version": "15.4"
      },
      "Apple Developer": null
    }
  },
  "system": {
    "macos": {
      "ventura": {
        "HOMEBREW_VERSION": "4.1.17",
        "HOMEBREW_PREFIX": "/opt/homebrew",
        "Homebrew/homebrew-core": "api",
        "CLT": "15.0.0.0.1.1694021235",
        "Xcode": "15.0.1",
        "macOS": "13.6"
      },
      "sonoma": {
        "HOMEBREW_VERSION": "4.3.1",
        "HOMEBREW_PREFIX": "/opt/homebrew",
        "Homebrew/homebrew-core": "api",
        "CLT": "15.3.0.0.1.1708646388",
        "Xcode": "15.4",
        "macOS": "14.4.1"
      }
    }
  }
}
