{
  "entries": {
    "tap": {
      "mongodb/brew": {
        "revision": "e1af7885954994e5f1a5af502a88d223c35a70d3"
      },
      "heroku/brew": {
        "revision": "61445bd76b04051a4f0755e031299d18bb0a4b29"
      }
    },
    "cask": {
      "1password": {
        "version": "8.9.11",
        "options": {
          "full_name": "1password"
        }
      },
      "adobe-acrobat-reader": {
        "version": "22.003.20281",
        "options": {
          "full_name": "adobe-acrobat-reader"
        }
      },
      "docker": {
        "version": "4.15.0,93002",
        "options": {
          "full_name": "docker"
        }
      },
      "google-chrome": {
        "version": "108.0.5359.124",
        "options": {
          "full_name": "google-chrome"
        }
      },
      "google-drive": {
        "version": "68.0.2",
        "options": {
          "full_name": "google-drive"
        }
      },
      "iterm2": {
        "version": "3.4.18",
        "options": {
          "full_name": "iterm2"
        }
      },
      "mongodb-compass": {
        "version": "1.34.1",
        "options": {
          "full_name": "mongodb-compass"
        }
      },
      "paintbrush": {
        "version": "2.6.0,20210402",
        "options": {
          "full_name": "paintbrush"
        }
      },
      "slack": {
        "version": "4.29.149",
        "options": {
          "full_name": "slack"
        }
      },
      "visual-studio-code": {
        "version": "1.74.1",
        "options": {
          "full_name": "visual-studio-code"
        }
      },
      "zoom": {
        "version": "5.12.9.13190",
        "options": {
          "full_name": "zoom"
        }
      },
      "expressvpn": {
        "version": "11.14.0.71145",
        "options": {
          "full_name": "expressvpn"
        }
      },
      "rectangle": {
        "version": "0.64,70",
        "options": {
          "full_name": "rectangle"
        }
      },
      "miniconda": {
        "version": "py39_4.12.0",
        "options": {
          "full_name": "miniconda"
        }
      },
      "discord": {
        "version": "0.0.270",
        "options": {
          "full_name": "discord"
        }
      },
      "ledger-live": {
        "version": "2.50.1",
        "options": {
          "full_name": "ledger-live"
        }
      },
      "krita": {
        "version": "5.1.4",
        "options": {
          "full_name": "krita"
        }
      },
      "vlc": {
        "version": "3.0.18",
        "options": {
          "full_name": "vlc"
        }
      },
      "exodus": {
        "version": "22.12.5",
        "options": {
          "full_name": "exodus"
        }
      },
      "ngrok": {
        "version": "3.1.0,7gHuLibjv89,a",
        "options": {
          "full_name": "ngrok"
        }
      },
      "flutter": {
        "version": "3.3.10",
        "options": {
          "full_name": "flutter"
        }
      }
    },
    "brew": {
      "git": {
        "version": "2.39.0",
        "bottle": {
          "rebuild": 0,
          "root_url": "https://ghcr.io/v2/homebrew/core",
          "files": {
            "arm64_ventura": {
              "cellar": "/opt/homebrew/Cellar",
              "url": "https://ghcr.io/v2/homebrew/core/git/blobs/sha256:008095cdb07f1bbb0020249e3f3077322eaad0f16e3fc9bc2214cfa991cc58ed",
              "sha256": "008095cdb07f1bbb0020249e3f3077322eaad0f16e3fc9bc2214cfa991cc58ed"
            },
            "arm64_monterey": {
              "cellar": "/opt/homebrew/Cellar",
              "url": "https://ghcr.io/v2/homebrew/core/git/blobs/sha256:6b78bc16509bd6b15d0ffae0dbf6e87517a80c5d22b780775bd0f87048e1a43d",
              "sha256": "6b78bc16509bd6b15d0ffae0dbf6e87517a80c5d22b780775bd0f87048e1a43d"
            },
            "arm64_big_sur": {
              "cellar": "/opt/homebrew/Cellar",
              "url": "https://ghcr.io/v2/homebrew/core/git/blobs/sha256:c982e453985bd084ed4881e19acd2b918469f10ad35d01b5179d2a7e8fad9b13",
              "sha256": "c982e453985bd084ed4881e19acd2b918469f10ad35d01b5179d2a7e8fad9b13"
            },
            "ventura": {
              "cellar": "/usr/local/Cellar",
              "url": "https://ghcr.io/v2/homebrew/core/git/blobs/sha256:f8e49ae6974d47ee1b7a3ed929ec5ff0524cca3f6bb92328a478a72019e7b24f",
              "sha256": "f8e49ae6974d47ee1b7a3ed929ec5ff0524cca3f6bb92328a478a72019e7b24f"
            },
            "monterey": {
              "cellar": "/usr/local/Cellar",
              "url": "https://ghcr.io/v2/homebrew/core/git/blobs/sha256:c97012f77d833b2ef076557d3d042108c49f4e15207f3304f8e79e9bc0d2d4e6",
              "sha256": "c97012f77d833b2ef076557d3d042108c49f4e15207f3304f8e79e9bc0d2d4e6"
            },
            "big_sur": {
              "cellar": "/usr/local/Cellar",
              "url": "https://ghcr.io/v2/homebrew/core/git/blobs/sha256:bef4488835140c1aebb852a6bb2ba4ca119ad88c410891d5878958697a51d026",
              "sha256": "bef4488835140c1aebb852a6bb2ba4ca119ad88c410891d5878958697a51d026"
            },
            "x86_64_linux": {
              "cellar": "/home/linuxbrew/.linuxbrew/Cellar",
              "url": "https://ghcr.io/v2/homebrew/core/git/blobs/sha256:d51a09cef4ca4b5f0cdb5995b4683e2492a7f62d57a783a8b1799c4e33913fe4",
              "sha256": "d51a09cef4ca4b5f0cdb5995b4683e2492a7f62d57a783a8b1799c4e33913fe4"
            }
          }
        }
      },
      "mas": {
        "version": "1.8.6",
        "bottle": {
          "rebuild": 0,
          "root_url": "https://ghcr.io/v2/homebrew/core",
          "files": {
            "arm64_ventura": {
              "cellar": ":any_skip_relocation",
              "url": "https://ghcr.io/v2/homebrew/core/mas/blobs/sha256:e49511dd1283813c4420aec9fc3b3167d18f9fdbb51d82b1e479b628d5312342",
              "sha256": "e49511dd1283813c4420aec9fc3b3167d18f9fdbb51d82b1e479b628d5312342"
            },
            "arm64_monterey": {
              "cellar": ":any_skip_relocation",
              "url": "https://ghcr.io/v2/homebrew/core/mas/blobs/sha256:379d46e2657be295321f1603dc1df28130ea0b5b264ceb192a9ba488d77c7a98",
              "sha256": "379d46e2657be295321f1603dc1df28130ea0b5b264ceb192a9ba488d77c7a98"
            },
            "arm64_big_sur": {
              "cellar": ":any_skip_relocation",
              "url": "https://ghcr.io/v2/homebrew/core/mas/blobs/sha256:918a1484de106940f7bebc936e1ded87d7b65652054b09204887ad0651937ec4",
              "sha256": "918a1484de106940f7bebc936e1ded87d7b65652054b09204887ad0651937ec4"
            },
            "ventura": {
              "cellar": ":any_skip_relocation",
              "url": "https://ghcr.io/v2/homebrew/core/mas/blobs/sha256:6ef7788e28c46cdc0f916812f49dfeb1fabf2240a8c36f33ce34bcfb9df1502f",
              "sha256": "6ef7788e28c46cdc0f916812f49dfeb1fabf2240a8c36f33ce34bcfb9df1502f"
            },
            "monterey": {
              "cellar": ":any_skip_relocation",
              "url": "https://ghcr.io/v2/homebrew/core/mas/blobs/sha256:6b313f2f66d028cb7782c108d6e502ce73ccb9c08fac3bece0b057fcce5c4689",
              "sha256": "6b313f2f66d028cb7782c108d6e502ce73ccb9c08fac3bece0b057fcce5c4689"
            },
            "big_sur": {
              "cellar": ":any_skip_relocation",
              "url": "https://ghcr.io/v2/homebrew/core/mas/blobs/sha256:50b50f51219143fcb69c730b52b74011a76104f66348ea727d0200f7b375ae25",
              "sha256": "50b50f51219143fcb69c730b52b74011a76104f66348ea727d0200f7b375ae25"
            },
            "catalina": {
              "cellar": ":any_skip_relocation",
              "url": "https://ghcr.io/v2/homebrew/core/mas/blobs/sha256:d241d3b9156b033f3d2c31684a44de726297e07fd9bd5e3ccc4c36e4f1c3baf3",
              "sha256": "d241d3b9156b033f3d2c31684a44de726297e07fd9bd5e3ccc4c36e4f1c3baf3"
            }
          }
        }
      },
      "mongodb-community": {
        "version": "6.0.1",
        "bottle": false
      },
      "pyenv": {
        "version": "2.2.4-1",
        "bottle": {
          "rebuild": 0,
          "root_url": "https://ghcr.io/v2/homebrew/core",
          "files": {
            "arm64_monterey": {
              "cellar": ":any",
              "url": "https://ghcr.io/v2/homebrew/core/pyenv/blobs/sha256:8ad522eb229b702dbe82444a11d5358ffa07d429d23c3ce689a5639a39d7568e",
              "sha256": "8ad522eb229b702dbe82444a11d5358ffa07d429d23c3ce689a5639a39d7568e"
            },
            "arm64_big_sur": {
              "cellar": ":any",
              "url": "https://ghcr.io/v2/homebrew/core/pyenv/blobs/sha256:24b0dc8ff20aa550332108314ecbd544bd056851b94915ee51d53dff3324b7ee",
              "sha256": "24b0dc8ff20aa550332108314ecbd544bd056851b94915ee51d53dff3324b7ee"
            },
            "monterey": {
              "cellar": ":any",
              "url": "https://ghcr.io/v2/homebrew/core/pyenv/blobs/sha256:f3961eb526561c9a75fd07946e689d5e9a005bd61c09b3f578ad56d58f6cc726",
              "sha256": "f3961eb526561c9a75fd07946e689d5e9a005bd61c09b3f578ad56d58f6cc726"
            },
            "big_sur": {
              "cellar": ":any",
              "url": "https://ghcr.io/v2/homebrew/core/pyenv/blobs/sha256:71dce77542c76862cde0a4a12a93fbe7825fd5e5ea5c6019fdc7d07d72bedcfc",
              "sha256": "71dce77542c76862cde0a4a12a93fbe7825fd5e5ea5c6019fdc7d07d72bedcfc"
            },
            "catalina": {
              "cellar": ":any",
              "url": "https://ghcr.io/v2/homebrew/core/pyenv/blobs/sha256:da9627aef795c2d7c90e50df2a742f62fd807c8c9bb5fccbaca4a2d427b4048f",
              "sha256": "da9627aef795c2d7c90e50df2a742f62fd807c8c9bb5fccbaca4a2d427b4048f"
            },
            "x86_64_linux": {
              "cellar": ":any_skip_relocation",
              "url": "https://ghcr.io/v2/homebrew/core/pyenv/blobs/sha256:ef3d3c3003adb228e39edeb2122d9a63caba8c7d731962497763808ad0ee1a8f",
              "sha256": "ef3d3c3003adb228e39edeb2122d9a63caba8c7d731962497763808ad0ee1a8f"
            }
          }
        }
      },
      "node": {
        "version": "19.3.0",
        "bottle": {
          "rebuild": 0,
          "root_url": "https://ghcr.io/v2/homebrew/core",
          "files": {
            "arm64_ventura": {
              "cellar": "/opt/homebrew/Cellar",
              "url": "https://ghcr.io/v2/homebrew/core/node/blobs/sha256:20cdbd3baf3f64d56f94219e6651a76140424b90664b6787162f2267bb908165",
              "sha256": "20cdbd3baf3f64d56f94219e6651a76140424b90664b6787162f2267bb908165"
            },
            "arm64_monterey": {
              "cellar": "/opt/homebrew/Cellar",
              "url": "https://ghcr.io/v2/homebrew/core/node/blobs/sha256:ffc0cf0a5e3dc983f159a902a270a64cec1ab2830f2a8924d40379fe5adb351a",
              "sha256": "ffc0cf0a5e3dc983f159a902a270a64cec1ab2830f2a8924d40379fe5adb351a"
            },
            "arm64_big_sur": {
              "cellar": "/opt/homebrew/Cellar",
              "url": "https://ghcr.io/v2/homebrew/core/node/blobs/sha256:606c36fe955671b141ea6d6d846ae47f886c43a4b9c656bc0e98829388186d0d",
              "sha256": "606c36fe955671b141ea6d6d846ae47f886c43a4b9c656bc0e98829388186d0d"
            },
            "ventura": {
              "cellar": "/usr/local/Cellar",
              "url": "https://ghcr.io/v2/homebrew/core/node/blobs/sha256:107f4a4160d9f87fefc3c413193625918f6439e629f02fef72debc50ae4a9712",
              "sha256": "107f4a4160d9f87fefc3c413193625918f6439e629f02fef72debc50ae4a9712"
            },
            "monterey": {
              "cellar": "/usr/local/Cellar",
              "url": "https://ghcr.io/v2/homebrew/core/node/blobs/sha256:f1ad6dc2e40e38bfdfbb7f82fa35e133049b01f60c0f339dc2cbdacf68790013",
              "sha256": "f1ad6dc2e40e38bfdfbb7f82fa35e133049b01f60c0f339dc2cbdacf68790013"
            },
            "big_sur": {
              "cellar": "/usr/local/Cellar",
              "url": "https://ghcr.io/v2/homebrew/core/node/blobs/sha256:1e396fa1297ed9e047c2d9eff13498a603f5643070309e60b891e36c2689a2d7",
              "sha256": "1e396fa1297ed9e047c2d9eff13498a603f5643070309e60b891e36c2689a2d7"
            },
            "x86_64_linux": {
              "cellar": "/home/linuxbrew/.linuxbrew/Cellar",
              "url": "https://ghcr.io/v2/homebrew/core/node/blobs/sha256:95ef71c5e896043291001ae8de0e62beca4c9e9974b62722d39c47328fe6d356",
              "sha256": "95ef71c5e896043291001ae8de0e62beca4c9e9974b62722d39c47328fe6d356"
            }
          }
        }
      },
      "dockutil": {
        "version": "2.0.5",
        "bottle": {
          "rebuild": 0,
          "root_url": "https://ghcr.io/v2/homebrew/core",
          "files": {
            "all": {
              "cellar": ":any_skip_relocation",
              "url": "https://ghcr.io/v2/homebrew/core/dockutil/blobs/sha256:f5f87d9e286c2b294bb157ac9f87baa2720fff044c7a92c0b80b9cb82db8a87e",
              "sha256": "f5f87d9e286c2b294bb157ac9f87baa2720fff044c7a92c0b80b9cb82db8a87e"
            }
          }
        }
      },
      "coreutils": {
        "version": "9.1",
        "bottle": {
          "rebuild": 0,
          "root_url": "https://ghcr.io/v2/homebrew/core",
          "files": {
            "arm64_ventura": {
              "cellar": "/opt/homebrew/Cellar",
              "url": "https://ghcr.io/v2/homebrew/core/coreutils/blobs/sha256:ae9dc313da2a3971c8e633d9f3262fd1bd431c303207b3346924aed60bb0965d",
              "sha256": "ae9dc313da2a3971c8e633d9f3262fd1bd431c303207b3346924aed60bb0965d"
            },
            "arm64_monterey": {
              "cellar": "/opt/homebrew/Cellar",
              "url": "https://ghcr.io/v2/homebrew/core/coreutils/blobs/sha256:6a9a4988eda436fb5bdb5969044579c2e618e21eee8c8bbe32614ad29fe56bd7",
              "sha256": "6a9a4988eda436fb5bdb5969044579c2e618e21eee8c8bbe32614ad29fe56bd7"
            },
            "arm64_big_sur": {
              "cellar": "/opt/homebrew/Cellar",
              "url": "https://ghcr.io/v2/homebrew/core/coreutils/blobs/sha256:85ef910aa223d48c0e73fc187aba54b86930c86f906e3d079ed0b114762bb24e",
              "sha256": "85ef910aa223d48c0e73fc187aba54b86930c86f906e3d079ed0b114762bb24e"
            },
            "ventura": {
              "cellar": "/usr/local/Cellar",
              "url": "https://ghcr.io/v2/homebrew/core/coreutils/blobs/sha256:4564009003601fb30335e57453cee93deaeab1eadf4473050e9e70198c21c892",
              "sha256": "4564009003601fb30335e57453cee93deaeab1eadf4473050e9e70198c21c892"
            },
            "monterey": {
              "cellar": "/usr/local/Cellar",
              "url": "https://ghcr.io/v2/homebrew/core/coreutils/blobs/sha256:7c9f988b4f9207415a5c96efd32376bc8cf2b280a7a36fbebb0b8fc334a14056",
              "sha256": "7c9f988b4f9207415a5c96efd32376bc8cf2b280a7a36fbebb0b8fc334a14056"
            },
            "big_sur": {
              "cellar": "/usr/local/Cellar",
              "url": "https://ghcr.io/v2/homebrew/core/coreutils/blobs/sha256:e446ef889d70bc377d67fa2d7f6a1fbc9faaee444a9e9086a1f5bd484069e5c0",
              "sha256": "e446ef889d70bc377d67fa2d7f6a1fbc9faaee444a9e9086a1f5bd484069e5c0"
            },
            "catalina": {
              "cellar": "/usr/local/Cellar",
              "url": "https://ghcr.io/v2/homebrew/core/coreutils/blobs/sha256:0d2117fa63dfcbb678c4e499f9ca0413c2c5bfa0a1bbdefde620434f2ead93a0",
              "sha256": "0d2117fa63dfcbb678c4e499f9ca0413c2c5bfa0a1bbdefde620434f2ead93a0"
            },
            "x86_64_linux": {
              "cellar": "/home/linuxbrew/.linuxbrew/Cellar",
              "url": "https://ghcr.io/v2/homebrew/core/coreutils/blobs/sha256:3c2fbec99344b50d620695d16197eb112cb8bee6d3f9e47cb682484755b91f38",
              "sha256": "3c2fbec99344b50d620695d16197eb112cb8bee6d3f9e47cb682484755b91f38"
            }
          }
        }
      },
      "heroku": {
        "version": "7.67.1",
        "bottle": false
      },
      "redis": {
        "version": "7.0.6",
        "bottle": {
          "rebuild": 0,
          "root_url": "https://ghcr.io/v2/homebrew/core",
          "files": {
            "arm64_ventura": {
              "cellar": ":any",
              "url": "https://ghcr.io/v2/homebrew/core/redis/blobs/sha256:d6871708dfbae5e2575e3a1c2463549688baef814fb2451a9f6752ed5f26bd52",
              "sha256": "d6871708dfbae5e2575e3a1c2463549688baef814fb2451a9f6752ed5f26bd52"
            },
            "arm64_monterey": {
              "cellar": ":any",
              "url": "https://ghcr.io/v2/homebrew/core/redis/blobs/sha256:fab34949b18f10dd29ee058ee266e5bcc00e83e1cd84bcb2a63dae30f32bcc1e",
              "sha256": "fab34949b18f10dd29ee058ee266e5bcc00e83e1cd84bcb2a63dae30f32bcc1e"
            },
            "arm64_big_sur": {
              "cellar": ":any",
              "url": "https://ghcr.io/v2/homebrew/core/redis/blobs/sha256:2e532087435e2fc0ea3105b7abc95388dc7c1cb630aa2f8558f9681bb77cc93b",
              "sha256": "2e532087435e2fc0ea3105b7abc95388dc7c1cb630aa2f8558f9681bb77cc93b"
            },
            "ventura": {
              "cellar": ":any",
              "url": "https://ghcr.io/v2/homebrew/core/redis/blobs/sha256:945ca3b3b0a41c3dacdba3eb7a8301831a06706dc41a686ceadac5e70bcc6601",
              "sha256": "945ca3b3b0a41c3dacdba3eb7a8301831a06706dc41a686ceadac5e70bcc6601"
            },
            "monterey": {
              "cellar": ":any",
              "url": "https://ghcr.io/v2/homebrew/core/redis/blobs/sha256:d8db070dfce9a2faba31ca3d628c7c95717b4b012729f777292dacdf2c7d5c00",
              "sha256": "d8db070dfce9a2faba31ca3d628c7c95717b4b012729f777292dacdf2c7d5c00"
            },
            "big_sur": {
              "cellar": ":any",
              "url": "https://ghcr.io/v2/homebrew/core/redis/blobs/sha256:838f774265186892e89573b08409b858387b2f8394fcea811d0a6f6b4f632889",
              "sha256": "838f774265186892e89573b08409b858387b2f8394fcea811d0a6f6b4f632889"
            },
            "x86_64_linux": {
              "cellar": ":any_skip_relocation",
              "url": "https://ghcr.io/v2/homebrew/core/redis/blobs/sha256:fb63211f7cca3d508d1a462cbe427d4186da09d0446581a74c12305ebfe5a1e5",
              "sha256": "fb63211f7cca3d508d1a462cbe427d4186da09d0446581a74c12305ebfe5a1e5"
            }
          }
        }
      },
      "chruby": {
        "version": "0.3.9",
        "bottle": {
          "rebuild": 0,
          "root_url": "https://ghcr.io/v2/homebrew/core",
          "files": {
            "arm64_big_sur": {
              "cellar": ":any_skip_relocation",
              "url": "https://ghcr.io/v2/homebrew/core/chruby/blobs/sha256:97ca44a014def181a1bd3cacb5ff86783c6fddb1d1262336e9765d14a7d5959a",
              "sha256": "97ca44a014def181a1bd3cacb5ff86783c6fddb1d1262336e9765d14a7d5959a"
            },
            "big_sur": {
              "cellar": ":any_skip_relocation",
              "url": "https://ghcr.io/v2/homebrew/core/chruby/blobs/sha256:16f188427ecc5432c18a004f567b73a8138fd2c2010d76821843e3804663fc02",
              "sha256": "16f188427ecc5432c18a004f567b73a8138fd2c2010d76821843e3804663fc02"
            },
            "catalina": {
              "cellar": ":any_skip_relocation",
              "url": "https://ghcr.io/v2/homebrew/core/chruby/blobs/sha256:004f825f798a41ffb3c9576aa3b77e7b8cef227287725818f5d3f1a779b12de6",
              "sha256": "004f825f798a41ffb3c9576aa3b77e7b8cef227287725818f5d3f1a779b12de6"
            },
            "mojave": {
              "cellar": ":any_skip_relocation",
              "url": "https://ghcr.io/v2/homebrew/core/chruby/blobs/sha256:4b3e7d6e76cd5d914b0bb4871a0a0f33c9b997a9c579ca4450191c87c3dc4f53",
              "sha256": "4b3e7d6e76cd5d914b0bb4871a0a0f33c9b997a9c579ca4450191c87c3dc4f53"
            },
            "high_sierra": {
              "cellar": ":any_skip_relocation",
              "url": "https://ghcr.io/v2/homebrew/core/chruby/blobs/sha256:d59074fe39429eb9979acd0e81e6b9a142aa73595971cee42ab91bbe850c6105",
              "sha256": "d59074fe39429eb9979acd0e81e6b9a142aa73595971cee42ab91bbe850c6105"
            },
            "sierra": {
              "cellar": ":any_skip_relocation",
              "url": "https://ghcr.io/v2/homebrew/core/chruby/blobs/sha256:17dc507695fed71749b5a58152d652bb7b92a4574f200b631a39f5f004e86cca",
              "sha256": "17dc507695fed71749b5a58152d652bb7b92a4574f200b631a39f5f004e86cca"
            },
            "el_capitan": {
              "cellar": ":any_skip_relocation",
              "url": "https://ghcr.io/v2/homebrew/core/chruby/blobs/sha256:ff70dff83817f093d39384a40d3dfb2aaccc1cbe475d58383d4ef157085f2c64",
              "sha256": "ff70dff83817f093d39384a40d3dfb2aaccc1cbe475d58383d4ef157085f2c64"
            },
            "x86_64_linux": {
              "cellar": ":any_skip_relocation",
              "url": "https://ghcr.io/v2/homebrew/core/chruby/blobs/sha256:bea6c750e5ce28f5a8ade003baef8a42bcbdf2b376e2d4ae8e12c7b3b112fef6",
              "sha256": "bea6c750e5ce28f5a8ade003baef8a42bcbdf2b376e2d4ae8e12c7b3b112fef6"
            },
            "all": {
              "cellar": ":any_skip_relocation",
              "url": "https://ghcr.io/v2/homebrew/core/chruby/blobs/sha256:977cf9319a21ddbbd26d3f0a43ed75825eb2a514bdce56b4045e5214732ec13b",
              "sha256": "977cf9319a21ddbbd26d3f0a43ed75825eb2a514bdce56b4045e5214732ec13b"
            }
          }
        }
      },
      "ruby-install": {
        "version": "0.8.5",
        "bottle": {
          "rebuild": 0,
          "root_url": "https://ghcr.io/v2/homebrew/core",
          "files": {
            "all": {
              "cellar": ":any_skip_relocation",
              "url": "https://ghcr.io/v2/homebrew/core/ruby-install/blobs/sha256:e0fe47d5a5ca9f84ffe59b40d48981341a0ab937342069d7f79c51dd4b95af0e",
              "sha256": "e0fe47d5a5ca9f84ffe59b40d48981341a0ab937342069d7f79c51dd4b95af0e"
            }
          }
        }
      }
    },
    "mas": {
      "GarageBand": {
        "id": "682658836",
        "version": "10.4.7"
      },
      "Xcode": {
        "id": "497799835",
        "version": "14.2"
      }
    }
  },
  "system": {
    "macos": {
      "monterey": {
        "HOMEBREW_VERSION": "3.6.15",
        "HOMEBREW_PREFIX": "/opt/homebrew",
        "Homebrew/homebrew-core": "6844e22b08748f10c69f43d64e1986d905001031",
        "CLT": "13.4.0.0.1.1651278267",
        "Xcode": "14.2",
        "macOS": "12.5.1"
      }
    }
  }
}
